Workbook

Sheet Visão Geral
C2: =SUM(TabelaGeral[Valor Aplicado],TabelaGeral[Dividendos]) -> 7031.81 | E2: =SUM(TabelaGeral[Dividendos]) -> 333.07
A6: ID | B6: Ativo | C6: Tipo Ativo | D6: Setor Segmento | E6: Quantidade | F6: Preço Médio | G6: Preço Atual | H6: Valor Aplicado | I6: Valor Total | J6: Dividendos | K6: Rentabilidade | L6: Valorização da Cota
A7: 1 | B7: #VALUE! | C7: FII | D7: Renda Urbana | E7: =SUMIFS(Aportes!H:H,Aportes!B:B,TabelaGeral[[#This Row],[ID ]]) -> 16 | F7: =AVERAGEIFS(Aportes!G:G,Aportes!B:B,TabelaGeral[[#This Row],[ID ]]) -> 99.949375 | G7: {=_FV(B7,"Preço")} -> 92.54 | H7: =SUMIFS(Aportes!I:I,Aportes!B:B,TabelaGeral[[#This Row],[ID ]]) -> 1599.19 | I7: =SUM(H7,J7) -> 1702.3 | J7: =SUMIFS(Dividendos!G:G,Dividendos!B:B,TabelaGeral[[#This Row],[ID ]]) -> 103.11 | K7: =(TabelaGeral[[#This Row],[Valor Total]]+TabelaGeral[[#This Row],[Dividendos]]-TabelaGeral[[#This Row],[Valor Aplicado]])/TabelaGeral[[#This Row],[Valor Aplicado]] -> 0.12895278 | L7: =(TabelaGeral[[#This Row],[Preço Atual]]-TabelaGeral[[#This Row],[Preço Médio]])/TabelaGeral[[#This Row],[Preço Médio]] -> -0.074131279
A8: 2 | B8: #VALUE! | C8: FII | D8: Logística | E8: =SUMIFS(Aportes!H:H,Aportes!B:B,TabelaGeral[[#This Row],[ID ]]) -> 14 | F8: =AVERAGEIFS(Aportes!G:G,Aportes!B:B,TabelaGeral[[#This Row],[ID ]]) -> 99.666429 | G8: {=_FV(B8,"Preço")} -> 103.32 | H8: =SUMIFS(Aportes!I:I,Aportes!B:B,TabelaGeral[[#This Row],[ID ]]) -> 1395.33 | I8: =SUM(H8,J8) -> 1482.06 | J8: =SUMIFS(Dividendos!G:G,Dividendos!B:B,TabelaGeral[[#This Row],[ID ]]) -> 86.73 | K8: =(TabelaGeral[[#This Row],[Valor Total]]+TabelaGeral[[#This Row],[Dividendos]]-TabelaGeral[[#This Row],[Valor Aplicado]])/TabelaGeral[[#This Row],[Valor Aplicado]] -> 0.12431468 | L8: =(TabelaGeral[[#This Row],[Preço Atual]]-TabelaGeral[[#This Row],[Preço Médio]])/TabelaGeral[[#This Row],[Preço Médio]] -> 0.036657995
A9: 3 | B9: #VALUE! | C9: FII | D9: Shopping | E9: =SUMIFS(Aportes!H:H,Aportes!B:B,TabelaGeral[[#This Row],[ID ]]) -> 14 | F9: =AVERAGEIFS(Aportes!G:G,Aportes!B:B,TabelaGeral[[#This Row],[ID ]]) -> 103.31429 | G9: {=_FV(B9,"Preço")} -> 110.7 | H9: =SUMIFS(Aportes!I:I,Aportes!B:B,TabelaGeral[[#This Row],[ID ]]) -> 1446.4 | I9: =SUM(H9,J9) -> 1548.52 | J9: =SUMIFS(Dividendos!G:G,Dividendos!B:B,TabelaGeral[[#This Row],[ID ]]) -> 102.12 | K9: =(TabelaGeral[[#This Row],[Valor Total]]+TabelaGeral[[#This Row],[Dividendos]]-TabelaGeral[[#This Row],[Valor Aplicado]])/TabelaGeral[[#This Row],[Valor Aplicado]] -> 0.14120575 | L9: =(TabelaGeral[[#This Row],[Preço Atual]]-TabelaGeral[[#This Row],[Preço Médio]])/TabelaGeral[[#This Row],[Preço Médio]] -> 0.071487832
A10: 4 | B10: #VALUE! | C10: FII | D10: Papel (CRI) | E10: =SUMIFS(Aportes!H:H,Aportes!B:B,TabelaGeral[[#This Row],[ID ]]) -> 57 | F10: =AVERAGEIFS(Aportes!G:G,Aportes!B:B,TabelaGeral[[#This Row],[ID ]]) -> 8.7438462 | G10: {=_FV(B10,"Preço")} -> 8.97 | H10: =SUMIFS(Aportes!I:I,Aportes!B:B,TabelaGeral[[#This Row],[ID ]]) -> 493.27 | I10: =SUM(H10,J10) -> 513.78 | J10: =SUMIFS(Dividendos!G:G,Dividendos!B:B,TabelaGeral[[#This Row],[ID ]]) -> 20.51 | K10: =(TabelaGeral[[#This Row],[Valor Total]]+TabelaGeral[[#This Row],[Dividendos]]-TabelaGeral[[#This Row],[Valor Aplicado]])/TabelaGeral[[#This Row],[Valor Aplicado]] -> 0.083159325 | L10: =(TabelaGeral[[#This Row],[Preço Atual]]-TabelaGeral[[#This Row],[Preço Médio]])/TabelaGeral[[#This Row],[Preço Médio]] -> 0.025864344
A11: 5 | B11: #VALUE! | C11: Ação | D11: Seguros | E11: =SUMIFS(Aportes!H:H,Aportes!B:B,TabelaGeral[[#This Row],[ID ]]) -> 10 | F11: =AVERAGEIFS(Aportes!G:G,Aportes!B:B,TabelaGeral[[#This Row],[ID ]]) -> 19.26 | G11: {=_FV(B11,"Preço")} -> 25.77 | H11: =SUMIFS(Aportes!I:I,Aportes!B:B,TabelaGeral[[#This Row],[ID ]]) -> 192.6 | I11: =SUM(H11,J11) -> 193.6 | J11: =SUMIFS(Dividendos!G:G,Dividendos!B:B,TabelaGeral[[#This Row],[ID ]]) -> 1 | K11: =(TabelaGeral[[#This Row],[Valor Total]]+TabelaGeral[[#This Row],[Dividendos]]-TabelaGeral[[#This Row],[Valor Aplicado]])/TabelaGeral[[#This Row],[Valor Aplicado]] -> 0.010384216 | L11: =(TabelaGeral[[#This Row],[Preço Atual]]-TabelaGeral[[#This Row],[Preço Médio]])/TabelaGeral[[#This Row],[Preço Médio]] -> 0.33800623
A12: 6 | B12: #VALUE! | C12: FII | D12: Renda Urbana | E12: =SUMIFS(Aportes!H:H,Aportes!B:B,TabelaGeral[[#This Row],[ID ]]) -> 55 | F12: =AVERAGEIFS(Aportes!G:G,Aportes!B:B,TabelaGeral[[#This Row],[ID ]]) -> 9.558 | G12: {=_FV(B12,"Preço")} -> 9.85 | H12: =SUMIFS(Aportes!I:I,Aportes!B:B,TabelaGeral[[#This Row],[ID ]]) -> 523.32 | I12: =SUM(H12,J12) -> 538.98 | J12: =SUMIFS(Dividendos!G:G,Dividendos!B:B,TabelaGeral[[#This Row],[ID ]]) -> 15.66 | K12: =(TabelaGeral[[#This Row],[Valor Total]]+TabelaGeral[[#This Row],[Dividendos]]-TabelaGeral[[#This Row],[Valor Aplicado]])/TabelaGeral[[#This Row],[Valor Aplicado]] -> 0.059848659 | L12: =(TabelaGeral[[#This Row],[Preço Atual]]-TabelaGeral[[#This Row],[Preço Médio]])/TabelaGeral[[#This Row],[Preço Médio]] -> 0.030550324
A13: 7 | B13: #VALUE! | C13: FII | D13: Híbrido | E13: =SUMIFS(Aportes!H:H,Aportes!B:B,TabelaGeral[[#This Row],[ID ]]) -> 32 | F13: =AVERAGEIFS(Aportes!G:G,Aportes!B:B,TabelaGeral[[#This Row],[ID ]]) -> 9.41 | G13: {=_FV(B13,"Preço")} -> 9.3 | H13: =SUMIFS(Aportes!I:I,Aportes!B:B,TabelaGeral[[#This Row],[ID ]]) -> 301.38 | I13: =SUM(H13,J13) -> 305.32 | J13: =SUMIFS(Dividendos!G:G,Dividendos!B:B,TabelaGeral[[#This Row],[ID ]]) -> 3.94 | K13: =(TabelaGeral[[#This Row],[Valor Total]]+TabelaGeral[[#This Row],[Dividendos]]-TabelaGeral[[#This Row],[Valor Aplicado]])/TabelaGeral[[#This Row],[Valor Aplicado]] -> 0.026146393 | L13: =(TabelaGeral[[#This Row],[Preço Atual]]-TabelaGeral[[#This Row],[Preço Médio]])/TabelaGeral[[#This Row],[Preço Médio]] -> -0.011689692
A14: 8 | B14: #VALUE! | C14: FII | D14: Logística | E14: =SUMIFS(Aportes!H:H,Aportes!B:B,TabelaGeral[[#This Row],[ID ]]) -> 2 | F14: =AVERAGEIFS(Aportes!G:G,Aportes!B:B,TabelaGeral[[#This Row],[ID ]]) -> 157.76 | G14: {=_FV(B14,"Preço")} -> 158.15 | H14: =SUMIFS(Aportes!I:I,Aportes!B:B,TabelaGeral[[#This Row],[ID ]]) -> 315.52 | I14: =SUM(H14,J14) -> 315.52 | J14: =SUMIFS(Dividendos!G:G,Dividendos!B:B,TabelaGeral[[#This Row],[ID ]]) -> 0 | K14: =(TabelaGeral[[#This Row],[Valor Total]]+TabelaGeral[[#This Row],[Dividendos]]-TabelaGeral[[#This Row],[Valor Aplicado]])/TabelaGeral[[#This Row],[Valor Aplicado]] -> 0 | L14: =(TabelaGeral[[#This Row],[Preço Atual]]-TabelaGeral[[#This Row],[Preço Médio]])/TabelaGeral[[#This Row],[Preço Médio]] -> 0.0024721095
A15: 9 | B15: #VALUE! | C15: FII | D15: Logística | E15: =SUMIFS(Aportes!H:H,Aportes!B:B,TabelaGeral[[#This Row],[ID ]]) -> 1 | F15: =AVERAGEIFS(Aportes!G:G,Aportes!B:B,TabelaGeral[[#This Row],[ID ]]) -> 102.94 | G15: {=_FV(B15,"Preço")} -> 101.53 | H15: =SUMIFS(Aportes!I:I,Aportes!B:B,TabelaGeral[[#This Row],[ID ]]) -> 102.94 | I15: =SUM(H15,J15) -> 102.94 | J15: =SUMIFS(Dividendos!G:G,Dividendos!B:B,TabelaGeral[[#This Row],[ID ]]) -> 0 | K15: =(TabelaGeral[[#This Row],[Valor Total]]+TabelaGeral[[#This Row],[Dividendos]]-TabelaGeral[[#This Row],[Valor Aplicado]])/TabelaGeral[[#This Row],[Valor Aplicado]] -> 0 | L15: =(TabelaGeral[[#This Row],[Preço Atual]]-TabelaGeral[[#This Row],[Preço Médio]])/TabelaGeral[[#This Row],[Preço Médio]] -> -0.013697299
A16: 10 | B16: #VALUE! | C16: Ação | D16: Holding Financeira | E16: =SUMIFS(Aportes!H:H,Aportes!B:B,TabelaGeral[[#This Row],[ID ]]) -> 12 | F16: =AVERAGEIFS(Aportes!G:G,Aportes!B:B,TabelaGeral[[#This Row],[ID ]]) -> 14.12 | G16: {=_FV(B16,"Preço")} -> 13.6 | H16: =SUMIFS(Aportes!I:I,Aportes!B:B,TabelaGeral[[#This Row],[ID ]]) -> 169.44 | I16: =SUM(H16,J16) -> 169.44 | J16: =SUMIFS(Dividendos!G:G,Dividendos!B:B,TabelaGeral[[#This Row],[ID ]]) -> 0 | K16: =(TabelaGeral[[#This Row],[Valor Total]]+TabelaGeral[[#This Row],[Dividendos]]-TabelaGeral[[#This Row],[Valor Aplicado]])/TabelaGeral[[#This Row],[Valor Aplicado]] -> 0 | L16: =(TabelaGeral[[#This Row],[Preço Atual]]-TabelaGeral[[#This Row],[Preço Médio]])/TabelaGeral[[#This Row],[Preço Médio]] -> -0.036827195
A17: 11 | B17: #VALUE! | C17: Ação | D17: Energia Elétrica | E17: 1 | F17: =AVERAGEIFS(Aportes!G:G,Aportes!B:B,TabelaGeral[[#This Row],[ID ]]) -> 31.87 | G17: {=_FV(B17,"Preço")} -> 32.26 | H17: =SUMIFS(Aportes!I:I,Aportes!B:B,TabelaGeral[[#This Row],[ID ]]) -> 159.35 | I17: =SUM(H17,J17) -> 159.35 | J17: =SUMIFS(Dividendos!G:G,Dividendos!B:B,TabelaGeral[[#This Row],[ID ]]) -> 0 | K17: =(TabelaGeral[[#This Row],[Valor Total]] + TabelaGeral[[#This Row],[Dividendos]] - TabelaGeral[[#This Row],[Valor Aplicado]]) / TabelaGeral[[#This Row],[Valor Aplicado]] -> 0 | L17: =(TabelaGeral[[#This Row],[Preço Atual]]-TabelaGeral[[#This Row],[Preço Médio]])/TabelaGeral[[#This Row],[Preço Médio]] -> 0.012237214

Sheet Ativos
B2: ID | C2: Ativo | D2: TipoAtivo | E2: SetorSegmento
B3: 1 | C3: TRXF11 | D3: FII | E3: Renda Urbana
B4: 2 | C4: BTLG11 | D4: FII | E4: Logística
B5: 3 | C5: XPML11 | D5: FII | E5: Shopping
B6: 4 | C6: KNSC11 | D6: FII | E6: Papel (CRI)
B7: 5 | C7: BBAS3 | D7: Ação | E7: Seguros
B8: 6 | C8: RBVA11 | D8: FII | E8: Renda Urbana
B9: 7 | C9: TRXY11 | D9: FII | E9: Híbrido
B10: 8 | C10: HGLG11 | D10: FII | E10: Logística
B11: 9 | C11: XPLG11 | D11: FII | E11: Logística
B12: 10 | C12: ITSA4 | D12: Ação | E12: Holding Financeira
B13: 11 | C13: EGIE3 | D13: Ação | E13: Energia Elétrica

Sheet Aportes
B2: ID | C2: Data | D2: Ativo | E2: Tipo | F2: Setor | G2: Valor Unitário | H2: Cotas | I2: Valor Total
B3: 1 | C3: 45665 | D3: =_xlfn.XLOOKUP(TabelaAporte[[#This Row],[ID]],Tabela1[[ID ]],Tabela1[Ativo]) -> TRXF11 | E3: =_xlfn.XLOOKUP(TabelaAporte[[#This Row],[ID]],Tabela1[[ID ]],Tabela1[[ TipoAtivo ]]) -> FII | F3: =_xlfn.XLOOKUP(TabelaAporte[[#This Row],[ID]],TabelaGeral[[ID ]],TabelaGeral[[ Setor Segmento]],) -> Renda Urbana | G3: 99.61 | H3: 1 | I3: =H3*G3 -> 99.61
B4: 2 | C4: 45665 | D4: =_xlfn.XLOOKUP(TabelaAporte[[#This Row],[ID]],Tabela1[[ID ]],Tabela1[Ativo]) -> BTLG11 | E4: =_xlfn.XLOOKUP(TabelaAporte[[#This Row],[ID]],Tabela1[[ID ]],Tabela1[[ TipoAtivo ]]) -> FII | F4: =_xlfn.XLOOKUP(TabelaAporte[[#This Row],[ID]],TabelaGeral[[ID ]],TabelaGeral[[ Setor Segmento]],) -> Logística | G4: 95.83 | H4: 1 | I4: =H4*G4 -> 95.83
B5: 3 | C5: 45665 | D5: =_xlfn.XLOOKUP(TabelaAporte[[#This Row],[ID]],Tabela1[[ID ]],Tabela1[Ativo]) -> XPML11 | E5: =_xlfn.XLOOKUP(TabelaAporte[[#This Row],[ID]],Tabela1[[ID ]],Tabela1[[ TipoAtivo ]]) -> FII | F5: =_xlfn.XLOOKUP(TabelaAporte[[#This Row],[ID]],TabelaGeral[[ID ]],TabelaGeral[[ Setor Segmento]],) -> Shopping | G5: 97.91 | H5: 1 | I5: =H5*G5 -> 97.91
B6: 1 | C6: 45694 | D6: =_xlfn.XLOOKUP(TabelaAporte[[#This Row],[ID]],Tabela1[[ID ]],Tabela1[Ativo]) -> TRXF11 | E6: =_xlfn.XLOOKUP(TabelaAporte[[#This Row],[ID]],Tabela1[[ID ]],Tabela1[[ TipoAtivo ]]) -> FII | F6: =_xlfn.XLOOKUP(TabelaAporte[[#This Row],[ID]],TabelaGeral[[ID ]],TabelaGeral[[ Setor Segmento]],) -> Renda Urbana | G6: 98.96 | H6: 1 | I6: =H6*G6 -> 98.96
B7: 2 | C7: 45694 | D7: =_xlfn.XLOOKUP(TabelaAporte[[#This Row],[ID]],Tabela1[[ID ]],Tabela1[Ativo]) -> BTLG11 | E7: =_xlfn.XLOOKUP(TabelaAporte[[#This Row],[ID]],Tabela1[[ID ]],Tabela1[[ TipoAtivo ]]) -> FII | F7: =_xlfn.XLOOKUP(TabelaAporte[[#This Row],[ID]],TabelaGeral[[ID ]],TabelaGeral[[ Setor Segmento]],) -> Logística | G7: 93.74 | H7: 1 | I7: =H7*G7 -> 93.74
B8: 3 | C8: 45694 | D8: =_xlfn.XLOOKUP(TabelaAporte[[#This Row],[ID]],Tabela1[[ID ]],Tabela1[Ativo]) -> XPML11 | E8: =_xlfn.XLOOKUP(TabelaAporte[[#This Row],[ID]],Tabela1[[ID ]],Tabela1[[ TipoAtivo ]]) -> FII | F8: =_xlfn.XLOOKUP(TabelaAporte[[#This Row],[ID]],TabelaGeral[[ID ]],TabelaGeral[[ Setor Segmento]],) -> Shopping | G8: 97.99 | H8: 1 | I8: =H8*G8 -> 97.99
B9: 1 | C9: 45726 | D9: =_xlfn.XLOOKUP(TabelaAporte[[#This Row],[ID]],Tabela1[[ID ]],Tabela1[Ativo]) -> TRXF11 | E9: =_xlfn.XLOOKUP(TabelaAporte[[#This Row],[ID]],Tabela1[[ID ]],Tabela1[[ TipoAtivo ]]) -> FII | F9: =_xlfn.XLOOKUP(TabelaAporte[[#This Row],[ID]],TabelaGeral[[ID ]],TabelaGeral[[ Setor Segmento]],) -> Renda Urbana | G9: 101.88 | H9: 1 | I9: =H9*G9 -> 101.88
B10: 2 | C10: 45726 | D10: =_xlfn.XLOOKUP(TabelaAporte[[#This Row],[ID]],Tabela1[[ID ]],Tabela1[Ativo]) -> BTLG11 | E10: =_xlfn.XLOOKUP(TabelaAporte[[#This Row],[ID]],Tabela1[[ID ]],Tabela1[[ TipoAtivo ]]) -> FII | F10: =_xlfn.XLOOKUP(TabelaAporte[[#This Row],[ID]],TabelaGeral[[ID ]],TabelaGeral[[ Setor Segmento]],) -> Logística | G10: 96.31 | H10: 1 | I10: =H10*G10 -> 96.31
B11: 3 | C11: 45726 | D11: =_xlfn.XLOOKUP(TabelaAporte[[#This Row],[ID]],Tabela1[[ID ]],Tabela1[Ativo]) -> XPML11 | E11: =_xlfn.XLOOKUP(TabelaAporte[[#This Row],[ID]],Tabela1[[ID ]],Tabela1[[ TipoAtivo ]]) -> FII | F11: =_xlfn.XLOOKUP(TabelaAporte[[#This Row],[ID]],TabelaGeral[[ID ]],TabelaGeral[[ Setor Segmento]],) -> Shopping | G11: 97.34 | H11: 1 | I11: =H11*G11 -> 97.34
B12: 1 | C12: 45751 | D12: =_xlfn.XLOOKUP(TabelaAporte[[#This Row],[ID]],Tabela1[[ID ]],Tabela1[Ativo]) -> TRXF11 | E12: =_xlfn.XLOOKUP(TabelaAporte[[#This Row],[ID]],Tabela1[[ID ]],Tabela1[[ TipoAtivo ]]) -> FII | F12: =_xlfn.XLOOKUP(TabelaAporte[[#This Row],[ID]],TabelaGeral[[ID ]],TabelaGeral[[ Setor Segmento]],) -> Renda Urbana | G12: 100.82 | H12: 1 | I12: =H12*G12 -> 100.82
B13: 2 | C13: 45751 | D13: =_xlfn.XLOOKUP(TabelaAporte[[#This Row],[ID]],Tabela1[[ID ]],Tabela1[Ativo]) -> BTLG11 | E13: =_xlfn.XLOOKUP(TabelaAporte[[#This Row],[ID]],Tabela1[[ID ]],Tabela1[[ TipoAtivo ]]) -> FII | F13: =_xlfn.XLOOKUP(TabelaAporte[[#This Row],[ID]],TabelaGeral[[ID ]],TabelaGeral[[ Setor Segmento]],) -> Logística | G13: 97.65 | H13: 1 | I13: =H13*G13 -> 97.65
B14: 3 | C14: 45751 | D14: =_xlfn.XLOOKUP(TabelaAporte[[#This Row],[ID]],Tabela1[[ID ]],Tabela1[Ativo]) -> XPML11 | E14: =_xlfn.XLOOKUP(TabelaAporte[[#This Row],[ID]],Tabela1[[ID ]],Tabela1[[ TipoAtivo ]]) -> FII | F14: =_xlfn.XLOOKUP(TabelaAporte[[#This Row],[ID]],TabelaGeral[[ID ]],TabelaGeral[[ Setor Segmento]],) -> Shopping | G14: 103.98 | H14: 1 | I14: =H14*G14 -> 103.98
... B74: 11 | C74: 46084 | D74: =_xlfn.XLOOKUP(TabelaAporte[[#This Row],[ID]],Tabela1[[ID ]],Tabela1[Ativo]) -> EGIE3 | E74: =_xlfn.XLOOKUP(TabelaAporte[[#This Row],[ID]],Tabela1[[ID ]],Tabela1[[ TipoAtivo ]]) -> Ação | F74: =_xlfn.XLOOKUP(TabelaAporte[[#This Row],[ID]],TabelaGeral[[ID ]],TabelaGeral[[ Setor Segmento]],) -> Energia Elétrica | G74: 31.87 | H74: 5 | I74: =H74*G74 -> 159.35
D75: =_xlfn.XLOOKUP(TabelaAporte[[#This Row],[ID]],Tabela1[[ID ]],Tabela1[Ativo]) -> #N/A | E75: =_xlfn.XLOOKUP(TabelaAporte[[#This Row],[ID]],Tabela1[[ID ]],Tabela1[[ TipoAtivo ]]) -> #N/A | F75: =_xlfn.XLOOKUP(TabelaAporte[[#This Row],[ID]],TabelaGeral[[ID ]],TabelaGeral[[ Setor Segmento]],) -> #N/A | I75: =H75*G75 -> 0
D76: =_xlfn.XLOOKUP(TabelaAporte[[#This Row],[ID]],Tabela1[[ID ]],Tabela1[Ativo]) -> #N/A | E76: =_xlfn.XLOOKUP(TabelaAporte[[#This Row],[ID]],Tabela1[[ID ]],Tabela1[[ TipoAtivo ]]) -> #N/A | F76: =_xlfn.XLOOKUP(TabelaAporte[[#This Row],[ID]],TabelaGeral[[ID ]],TabelaGeral[[ Setor Segmento]],) -> #N/A | I76: =H76*G76 -> 0
D77: =_xlfn.XLOOKUP(TabelaAporte[[#This Row],[ID]],Tabela1[[ID ]],Tabela1[Ativo]) -> #N/A | E77: =_xlfn.XLOOKUP(TabelaAporte[[#This Row],[ID]],Tabela1[[ID ]],Tabela1[[ TipoAtivo ]]) -> #N/A | F77: =_xlfn.XLOOKUP(TabelaAporte[[#This Row],[ID]],TabelaGeral[[ID ]],TabelaGeral[[ Setor Segmento]],) -> #N/A | I77: =H77*G77 -> 0
D78: =_xlfn.XLOOKUP(TabelaAporte[[#This Row],[ID]],Tabela1[[ID ]],Tabela1[Ativo]) -> #N/A | E78: =_xlfn.XLOOKUP(TabelaAporte[[#This Row],[ID]],Tabela1[[ID ]],Tabela1[[ TipoAtivo ]]) -> #N/A | F78: =_xlfn.XLOOKUP(TabelaAporte[[#This Row],[ID]],TabelaGeral[[ID ]],TabelaGeral[[ Setor Segmento]],) -> #N/A | I78: =H78*G78 -> 0
D79: =_xlfn.XLOOKUP(TabelaAporte[[#This Row],[ID]],Tabela1[[ID ]],Tabela1[Ativo]) -> #N/A | E79: =_xlfn.XLOOKUP(TabelaAporte[[#This Row],[ID]],Tabela1[[ID ]],Tabela1[[ TipoAtivo ]]) -> #N/A | F79: =_xlfn.XLOOKUP(TabelaAporte[[#This Row],[ID]],TabelaGeral[[ID ]],TabelaGeral[[ Setor Segmento]],) -> #N/A | I79: =H79*G79 -> 0
D80: =_xlfn.XLOOKUP(TabelaAporte[[#This Row],[ID]],Tabela1[[ID ]],Tabela1[Ativo]) -> #N/A | E80: =_xlfn.XLOOKUP(TabelaAporte[[#This Row],[ID]],Tabela1[[ID ]],Tabela1[[ TipoAtivo ]]) -> #N/A | F80: =_xlfn.XLOOKUP(TabelaAporte[[#This Row],[ID]],TabelaGeral[[ID ]],TabelaGeral[[ Setor Segmento]],) -> #N/A | I80: =H80*G80 -> 0
D81: =_xlfn.XLOOKUP(TabelaAporte[[#This Row],[ID]],Tabela1[[ID ]],Tabela1[Ativo]) -> #N/A | E81: =_xlfn.XLOOKUP(TabelaAporte[[#This Row],[ID]],Tabela1[[ID ]],Tabela1[[ TipoAtivo ]]) -> #N/A | F81: =_xlfn.XLOOKUP(TabelaAporte[[#This Row],[ID]],TabelaGeral[[ID ]],TabelaGeral[[ Setor Segmento]],) -> #N/A | I81: =H81*G81 -> 0
D82: =_xlfn.XLOOKUP(TabelaAporte[[#This Row],[ID]],Tabela1[[ID ]],Tabela1[Ativo]) -> #N/A | E82: =_xlfn.XLOOKUP(TabelaAporte[[#This Row],[ID]],Tabela1[[ID ]],Tabela1[[ TipoAtivo ]]) -> #N/A | F82: =_xlfn.XLOOKUP(TabelaAporte[[#This Row],[ID]],TabelaGeral[[ID ]],TabelaGeral[[ Setor Segmento]],) -> #N/A | I82: =H82*G82 -> 0
D83: =_xlfn.XLOOKUP(TabelaAporte[[#This Row],[ID]],Tabela1[[ID ]],Tabela1[Ativo]) -> #N/A | E83: =_xlfn.XLOOKUP(TabelaAporte[[#This Row],[ID]],Tabela1[[ID ]],Tabela1[[ TipoAtivo ]]) -> #N/A | F83: =_xlfn.XLOOKUP(TabelaAporte[[#This Row],[ID]],TabelaGeral[[ID ]],TabelaGeral[[ Setor Segmento]],) -> #N/A | I83: =H83*G83 -> 0
D84: =_xlfn.XLOOKUP(TabelaAporte[[#This Row],[ID]],Tabela1[[ID ]],Tabela1[Ativo]) -> #N/A | E84: =_xlfn.XLOOKUP(TabelaAporte[[#This Row],[ID]],Tabela1[[ID ]],Tabela1[[ TipoAtivo ]]) -> #N/A | F84: =_xlfn.XLOOKUP(TabelaAporte[[#This Row],[ID]],TabelaGeral[[ID ]],TabelaGeral[[ Setor Segmento]],) -> #N/A | I84: =H84*G84 -> 0
D85: =_xlfn.XLOOKUP(TabelaAporte[[#This Row],[ID]],Tabela1[[ID ]],Tabela1[Ativo]) -> #N/A | E85: =_xlfn.XLOOKUP(TabelaAporte[[#This Row],[ID]],Tabela1[[ID ]],Tabela1[[ TipoAtivo ]]) -> #N/A | F85: =_xlfn.XLOOKUP(TabelaAporte[[#This Row],[ID]],TabelaGeral[[ID ]],TabelaGeral[[ Setor Segmento]],) -> #N/A | I85: =H85*G85 -> 0
D86: =_xlfn.XLOOKUP(TabelaAporte[[#This Row],[ID]],Tabela1[[ID ]],Tabela1[Ativo]) -> #N/A | E86: =_xlfn.XLOOKUP(TabelaAporte[[#This Row],[ID]],Tabela1[[ID ]],Tabela1[[ TipoAtivo ]]) -> #N/A | F86: =_xlfn.XLOOKUP(TabelaAporte[[#This Row],[ID]],TabelaGeral[[ID ]],TabelaGeral[[ Setor Segmento]],) -> #N/A | I86: =H86*G86 -> 0
... D308: =_xlfn.XLOOKUP(TabelaAporte[[#This Row],[ID]],Tabela1[[ID ]],Tabela1[Ativo]) -> #N/A | E308: =_xlfn.XLOOKUP(TabelaAporte[[#This Row],[ID]],Tabela1[[ID ]],Tabela1[[ TipoAtivo ]]) -> #N/A | F308: =_xlfn.XLOOKUP(TabelaAporte[[#This Row],[ID]],TabelaGeral[[ID ]],TabelaGeral[[ Setor Segmento]],) -> #N/A | I308: =H308*G308 -> 0

Sheet Dividendos
B2: ID | C2: Data | D2: Ativo | E2: Tipo | F2: Setor | G2: Dividendo
B3: 2 | C3: 45679 | D3: =_xlfn.XLOOKUP(TabelaDividendos[[#This Row],[ID]],Tabela1[[ID ]],Tabela1[Ativo]) -> BTLG11 | E3: =_xlfn.XLOOKUP(TabelaDividendos[[#This Row],[ID]],TabelaGeral[[ID ]],TabelaGeral[[ Tipo Ativo ]]) -> FII | F3: =_xlfn.XLOOKUP(TabelaDividendos[[#This Row],[ID]],TabelaGeral[[ID ]],TabelaGeral[[ Setor Segmento]]) -> Logística | G3: 0.86
B4: 3 | C4: 45679 | D4: =_xlfn.XLOOKUP(TabelaDividendos[[#This Row],[ID]],Tabela1[[ID ]],Tabela1[Ativo]) -> XPML11 | E4: =_xlfn.XLOOKUP(TabelaDividendos[[#This Row],[ID]],TabelaGeral[[ID ]],TabelaGeral[[ Tipo Ativo ]]) -> FII | F4: =_xlfn.XLOOKUP(TabelaDividendos[[#This Row],[ID]],TabelaGeral[[ID ]],TabelaGeral[[ Setor Segmento]]) -> Shopping | G4: 0.92
B5: 1 | C5: 45702 | D5: =_xlfn.XLOOKUP(TabelaDividendos[[#This Row],[ID]],Tabela1[[ID ]],Tabela1[Ativo]) -> TRXF11 | E5: =_xlfn.XLOOKUP(TabelaDividendos[[#This Row],[ID]],TabelaGeral[[ID ]],TabelaGeral[[ Tipo Ativo ]]) -> FII | F5: =_xlfn.XLOOKUP(TabelaDividendos[[#This Row],[ID]],TabelaGeral[[ID ]],TabelaGeral[[ Setor Segmento]]) -> Renda Urbana | G5: 0.93
B6: 2 | C6: 45713 | D6: =_xlfn.XLOOKUP(TabelaDividendos[[#This Row],[ID]],Tabela1[[ID ]],Tabela1[Ativo]) -> BTLG11 | E6: =_xlfn.XLOOKUP(TabelaDividendos[[#This Row],[ID]],TabelaGeral[[ID ]],TabelaGeral[[ Tipo Ativo ]]) -> FII | F6: =_xlfn.XLOOKUP(TabelaDividendos[[#This Row],[ID]],TabelaGeral[[ID ]],TabelaGeral[[ Setor Segmento]]) -> Logística | G6: 1.56
B7: 3 | C7: 45713 | D7: =_xlfn.XLOOKUP(TabelaDividendos[[#This Row],[ID]],Tabela1[[ID ]],Tabela1[Ativo]) -> XPML11 | E7: =_xlfn.XLOOKUP(TabelaDividendos[[#This Row],[ID]],TabelaGeral[[ID ]],TabelaGeral[[ Tipo Ativo ]]) -> FII | F7: =_xlfn.XLOOKUP(TabelaDividendos[[#This Row],[ID]],TabelaGeral[[ID ]],TabelaGeral[[ Setor Segmento]]) -> Shopping | G7: 1.84
B8: 1 | C8: 45734 | D8: =_xlfn.XLOOKUP(TabelaDividendos[[#This Row],[ID]],Tabela1[[ID ]],Tabela1[Ativo]) -> TRXF11 | E8: =_xlfn.XLOOKUP(TabelaDividendos[[#This Row],[ID]],TabelaGeral[[ID ]],TabelaGeral[[ Tipo Ativo ]]) -> FII | F8: =_xlfn.XLOOKUP(TabelaDividendos[[#This Row],[ID]],TabelaGeral[[ID ]],TabelaGeral[[ Setor Segmento]]) -> Renda Urbana | G8: 1.86
B9: 2 | C9: 45741 | D9: =_xlfn.XLOOKUP(TabelaDividendos[[#This Row],[ID]],Tabela1[[ID ]],Tabela1[Ativo]) -> BTLG11 | E9: =_xlfn.XLOOKUP(TabelaDividendos[[#This Row],[ID]],TabelaGeral[[ID ]],TabelaGeral[[ Tipo Ativo ]]) -> FII | F9: =_xlfn.XLOOKUP(TabelaDividendos[[#This Row],[ID]],TabelaGeral[[ID ]],TabelaGeral[[ Setor Segmento]]) -> Logística | G9: 2.34
B10: 3 | C10: 45741 | D10: =_xlfn.XLOOKUP(TabelaDividendos[[#This Row],[ID]],Tabela1[[ID ]],Tabela1[Ativo]) -> XPML11 | E10: =_xlfn.XLOOKUP(TabelaDividendos[[#This Row],[ID]],TabelaGeral[[ID ]],TabelaGeral[[ Tipo Ativo ]]) -> FII | F10: =_xlfn.XLOOKUP(TabelaDividendos[[#This Row],[ID]],TabelaGeral[[ID ]],TabelaGeral[[ Setor Segmento]]) -> Shopping | G10: 2.76
B11: 1 | C11: 45761 | D11: =_xlfn.XLOOKUP(TabelaDividendos[[#This Row],[ID]],Tabela1[[ID ]],Tabela1[Ativo]) -> TRXF11 | E11: =_xlfn.XLOOKUP(TabelaDividendos[[#This Row],[ID]],TabelaGeral[[ID ]],TabelaGeral[[ Tipo Ativo ]]) -> FII | F11: =_xlfn.XLOOKUP(TabelaDividendos[[#This Row],[ID]],TabelaGeral[[ID ]],TabelaGeral[[ Setor Segmento]]) -> Renda Urbana | G11: 2.79
B12: 2 | C12: 45772 | D12: =_xlfn.XLOOKUP(TabelaDividendos[[#This Row],[ID]],Tabela1[[ID ]],Tabela1[Ativo]) -> BTLG11 | E12: =_xlfn.XLOOKUP(TabelaDividendos[[#This Row],[ID]],TabelaGeral[[ID ]],TabelaGeral[[ Tipo Ativo ]]) -> FII | F12: =_xlfn.XLOOKUP(TabelaDividendos[[#This Row],[ID]],TabelaGeral[[ID ]],TabelaGeral[[ Setor Segmento]]) -> Logística | G12: 3.12
B13: 3 | C13: 45772 | D13: =_xlfn.XLOOKUP(TabelaDividendos[[#This Row],[ID]],Tabela1[[ID ]],Tabela1[Ativo]) -> XPML11 | E13: =_xlfn.XLOOKUP(TabelaDividendos[[#This Row],[ID]],TabelaGeral[[ID ]],TabelaGeral[[ Tipo Ativo ]]) -> FII | F13: =_xlfn.XLOOKUP(TabelaDividendos[[#This Row],[ID]],TabelaGeral[[ID ]],TabelaGeral[[ Setor Segmento]]) -> Shopping | G13: 3.68
B14: 4 | C14: 45791 | D14: =_xlfn.XLOOKUP(TabelaDividendos[[#This Row],[ID]],Tabela1[[ID ]],Tabela1[Ativo]) -> KNSC11 | E14: =_xlfn.XLOOKUP(TabelaDividendos[[#This Row],[ID]],TabelaGeral[[ID ]],TabelaGeral[[ Tipo Ativo ]]) -> FII | F14: =_xlfn.XLOOKUP(TabelaDividendos[[#This Row],[ID]],TabelaGeral[[ID ]],TabelaGeral[[ Setor Segmento]]) -> Papel (CRI) | G14: 0.22
... B61: 3 | C61: 46078 | D61: =_xlfn.XLOOKUP(TabelaDividendos[[#This Row],[ID]],Tabela1[[ID ]],Tabela1[Ativo]) -> XPML11 | E61: =_xlfn.XLOOKUP(TabelaDividendos[[#This Row],[ID]],TabelaGeral[[ID ]],TabelaGeral[[ Tipo Ativo ]]) -> FII | F61: =_xlfn.XLOOKUP(TabelaDividendos[[#This Row],[ID]],TabelaGeral[[ID ]],TabelaGeral[[ Setor Segmento]]) -> Shopping | G61: 12.88
D62: =_xlfn.XLOOKUP(TabelaDividendos[[#This Row],[ID]],Tabela1[[ID ]],Tabela1[Ativo]) -> #N/A | E62: =_xlfn.XLOOKUP(TabelaDividendos[[#This Row],[ID]],TabelaGeral[[ID ]],TabelaGeral[[ Tipo Ativo ]]) -> #N/A | F62: =_xlfn.XLOOKUP(TabelaDividendos[[#This Row],[ID]],TabelaGeral[[ID ]],TabelaGeral[[ Setor Segmento]]) -> #N/A
D63: =_xlfn.XLOOKUP(TabelaDividendos[[#This Row],[ID]],Tabela1[[ID ]],Tabela1[Ativo]) -> #N/A | E63: =_xlfn.XLOOKUP(TabelaDividendos[[#This Row],[ID]],TabelaGeral[[ID ]],TabelaGeral[[ Tipo Ativo ]]) -> #N/A | F63: =_xlfn.XLOOKUP(TabelaDividendos[[#This Row],[ID]],TabelaGeral[[ID ]],TabelaGeral[[ Setor Segmento]]) -> #N/A
D64: =_xlfn.XLOOKUP(TabelaDividendos[[#This Row],[ID]],Tabela1[[ID ]],Tabela1[Ativo]) -> #N/A | E64: =_xlfn.XLOOKUP(TabelaDividendos[[#This Row],[ID]],TabelaGeral[[ID ]],TabelaGeral[[ Tipo Ativo ]]) -> #N/A | F64: =_xlfn.XLOOKUP(TabelaDividendos[[#This Row],[ID]],TabelaGeral[[ID ]],TabelaGeral[[ Setor Segmento]]) -> #N/A
D65: =_xlfn.XLOOKUP(TabelaDividendos[[#This Row],[ID]],Tabela1[[ID ]],Tabela1[Ativo]) -> #N/A | E65: =_xlfn.XLOOKUP(TabelaDividendos[[#This Row],[ID]],TabelaGeral[[ID ]],TabelaGeral[[ Tipo Ativo ]]) -> #N/A | F65: =_xlfn.XLOOKUP(TabelaDividendos[[#This Row],[ID]],TabelaGeral[[ID ]],TabelaGeral[[ Setor Segmento]]) -> #N/A
D66: =_xlfn.XLOOKUP(TabelaDividendos[[#This Row],[ID]],Tabela1[[ID ]],Tabela1[Ativo]) -> #N/A | E66: =_xlfn.XLOOKUP(TabelaDividendos[[#This Row],[ID]],TabelaGeral[[ID ]],TabelaGeral[[ Tipo Ativo ]]) -> #N/A | F66: =_xlfn.XLOOKUP(TabelaDividendos[[#This Row],[ID]],TabelaGeral[[ID ]],TabelaGeral[[ Setor Segmento]]) -> #N/A
D67: =_xlfn.XLOOKUP(TabelaDividendos[[#This Row],[ID]],Tabela1[[ID ]],Tabela1[Ativo]) -> #N/A | E67: =_xlfn.XLOOKUP(TabelaDividendos[[#This Row],[ID]],TabelaGeral[[ID ]],TabelaGeral[[ Tipo Ativo ]]) -> #N/A | F67: =_xlfn.XLOOKUP(TabelaDividendos[[#This Row],[ID]],TabelaGeral[[ID ]],TabelaGeral[[ Setor Segmento]]) -> #N/A
D68: =_xlfn.XLOOKUP(TabelaDividendos[[#This Row],[ID]],Tabela1[[ID ]],Tabela1[Ativo]) -> #N/A | E68: =_xlfn.XLOOKUP(TabelaDividendos[[#This Row],[ID]],TabelaGeral[[ID ]],TabelaGeral[[ Tipo Ativo ]]) -> #N/A | F68: =_xlfn.XLOOKUP(TabelaDividendos[[#This Row],[ID]],TabelaGeral[[ID ]],TabelaGeral[[ Setor Segmento]]) -> #N/A
D69: =_xlfn.XLOOKUP(TabelaDividendos[[#This Row],[ID]],Tabela1[[ID ]],Tabela1[Ativo]) -> #N/A | E69: =_xlfn.XLOOKUP(TabelaDividendos[[#This Row],[ID]],TabelaGeral[[ID ]],TabelaGeral[[ Tipo Ativo ]]) -> #N/A | F69: =_xlfn.XLOOKUP(TabelaDividendos[[#This Row],[ID]],TabelaGeral[[ID ]],TabelaGeral[[ Setor Segmento]]) -> #N/A
D70: =_xlfn.XLOOKUP(TabelaDividendos[[#This Row],[ID]],Tabela1[[ID ]],Tabela1[Ativo]) -> #N/A | E70: =_xlfn.XLOOKUP(TabelaDividendos[[#This Row],[ID]],TabelaGeral[[ID ]],TabelaGeral[[ Tipo Ativo ]]) -> #N/A | F70: =_xlfn.XLOOKUP(TabelaDividendos[[#This Row],[ID]],TabelaGeral[[ID ]],TabelaGeral[[ Setor Segmento]]) -> #N/A
D71: =_xlfn.XLOOKUP(TabelaDividendos[[#This Row],[ID]],Tabela1[[ID ]],Tabela1[Ativo]) -> #N/A | E71: =_xlfn.XLOOKUP(TabelaDividendos[[#This Row],[ID]],TabelaGeral[[ID ]],TabelaGeral[[ Tipo Ativo ]]) -> #N/A | F71: =_xlfn.XLOOKUP(TabelaDividendos[[#This Row],[ID]],TabelaGeral[[ID ]],TabelaGeral[[ Setor Segmento]]) -> #N/A
D72: =_xlfn.XLOOKUP(TabelaDividendos[[#This Row],[ID]],Tabela1[[ID ]],Tabela1[Ativo]) -> #N/A | E72: =_xlfn.XLOOKUP(TabelaDividendos[[#This Row],[ID]],TabelaGeral[[ID ]],TabelaGeral[[ Tipo Ativo ]]) -> #N/A | F72: =_xlfn.XLOOKUP(TabelaDividendos[[#This Row],[ID]],TabelaGeral[[ID ]],TabelaGeral[[ Setor Segmento]]) -> #N/A
D73: =_xlfn.XLOOKUP(TabelaDividendos[[#This Row],[ID]],Tabela1[[ID ]],Tabela1[Ativo]) -> #N/A | E73: =_xlfn.XLOOKUP(TabelaDividendos[[#This Row],[ID]],TabelaGeral[[ID ]],TabelaGeral[[ Tipo Ativo ]]) -> #N/A | F73: =_xlfn.XLOOKUP(TabelaDividendos[[#This Row],[ID]],TabelaGeral[[ID ]],TabelaGeral[[ Setor Segmento]]) -> #N/A
... D228: =_xlfn.XLOOKUP(TabelaDividendos[[#This Row],[ID]],Tabela1[[ID ]],Tabela1[Ativo]) -> #N/A | E228: =_xlfn.XLOOKUP(TabelaDividendos[[#This Row],[ID]],TabelaGeral[[ID ]],TabelaGeral[[ Tipo Ativo ]]) -> #N/A | F228: =_xlfn.XLOOKUP(TabelaDividendos[[#This Row],[ID]],TabelaGeral[[ID ]],TabelaGeral[[ Setor Segmento]]) -> #N/A

Sheet Gráficos&Projeções
B2: DIVIDENDOS 2025
C3: 45658 | D3: 45689 | E3: 45717 | F3: 45748 | G3: 45778 | H3: 45809 | I3: 45839 | J3: 45870 | K3: 45901 | L3: 45931 | M3: 45962 | N3: 45992 | O3: TOTAL | P3: MEDIA
B4: TRXF11 | C4: 0 | D4: 0.93 | E4: 1.86 | F4: 2.79 | G4: 3.72 | H4: 4.65 | I4: 9.06 | J4: 6.51 | K4: 9.3 | L4: 10.23 | M4: 11.16 | N4: 13.02 | O4: =SUM(C4:N4) -> 73.23 | P4: =AVERAGE(C4:N4) -> 6.1025
B5: BTLG11 | C5: 0.87 | D5: 1.56 | E5: 2.34 | F5: 3.12 | G5: 3.9 | H5: 4.68 | I5: 5.46 | J5: 7.8 | K5: 8.69 | L5: 9.48 | M5: 9.48 | N5: 9.48 | O5: =SUM(C5:N5) -> 66.86 | P5: =AVERAGE(C5:N5) -> 5.5716667
B6: XPML11 | C6: 0.92 | D6: 1.84 | E6: 2.76 | F6: 3.68 | G6: 4.6 | H6: 5.52 | I6: 6.44 | J6: 8.28 | K6: 9.2 | L6: 10.12 | M6: 11.04 | N6: 11.96 | O6: =SUM(C6:N6) -> 76.36 | P6: =AVERAGE(C6:N6) -> 6.3633333
B7: KNSC11 | C7: 0 | D7: 0 | E7: 0 | F7: 0 | G7: 0.22 | H7: 0.2 | I7: 0.81 | J7: 1.3 | K7: 1.44 | L7: 1.6 | M7: 2.25 | N7: 3.33 | O7: =SUM(C7:N7) -> 11.15 | P7: =AVERAGE(C7:N7) -> 0.92916667
B8: BBSA3 | C8: 0 | D8: 0 | E8: 0 | F8: 0 | G8: 0 | H8: 0 | I8: 0 | J8: 0 | K8: 0 | L8: 0 | M8: 0 | N8: 1 | O8: =SUM(C8:N8) -> 1 | P8: =AVERAGE(C8:N8) -> 0.083333333
B9: RBVA11 | C9: 0 | D9: 0 | E9: 0 | F9: 0 | G9: 0 | H9: 0 | I9: 0 | J9: 0 | K9: 0 | L9: 1.26 | M9: 2.25 | N9: 3.15 | O9: =SUM(C9:N9) -> 6.66 | P9: =AVERAGE(C9:N9) -> 0.555
B10: Total 2025 | C10: =SUM(C4:C9) -> 1.79 | D10: =SUM(D4:D9) -> 4.33 | E10: =SUM(E4:E9) -> 6.96 | F10: =SUM(F4:F9) -> 9.59 | G10: =SUM(G4:G9) -> 12.44 | H10: =SUM(H4:H9) -> 15.05 | I10: =SUM(I4:I9) -> 21.77 | J10: =SUM(J4:J9) -> 23.89 | ... O10: =SUM(O4:O9) -> 235.26
B29: DIVIDENDOS 2026
C30: 46023 | D30: 46054 | E30: 46082 | F30: 46113 | G30: 46143 | H30: 46174 | I30: 46204 | J30: 46235 | K30: 46266 | L30: 46296 | M30: 46327 | N30: 46357 | O30: TOTAL | P30: MEDIA
B31: TRXF11 | C31: 15 | D31: 14.88 | O31: =SUM(C31:N31) -> 29.88 | P31: =AVERAGE(C31:N31) -> 14.94
B32: TRXY11 | C32: 1.3 | D32: 2.64 | O32: =SUM(C32:N32) -> 3.94 | P32: =AVERAGE(C32:N32) -> 1.97
B33: BTLG11 | C33: 9.48 | D33: 10.4 | O33: =SUM(C33:N33) -> 19.88 | P33: =AVERAGE(C33:N33) -> 9.94
B34: XPML11 | C34: 12.88 | D34: 12.88 | O34: =SUM(C34:N34) -> 25.76 | P34: =AVERAGE(C34:N34) -> 12.88
B35: KNSC11 | C35: 4.23 | D35: 5.13 | O35: =SUM(C35:N35) -> 9.36 | P35: =AVERAGE(C35:N35) -> 4.68
B36: BBSA3 | C36: - | D36: - | O36: =SUM(C36:N36) -> 0 | P36: =AVERAGE(C36:N36) -> #DIV/0!
B37: ITSA4 | C37: - | D37: - | O37: =SUM(C37:N37) -> 0 | P37: =AVERAGE(C37:N37) -> #DIV/0!
B38: HGLG11 | C38: - | D38: - | O38: =SUM(C38:N38) -> 0 | P38: =AVERAGE(C38:N38) -> #DIV/0!
B39: XPLG11 | C39: - | D39: - | O39: =SUM(C39:N39) -> 0 | P39: =AVERAGE(C39:N39) -> #DIV/0!
B40: RBVA11 | C40: 4.05 | D40: 4.95 | O40: =SUM(C40:N40) -> 9 | P40: =AVERAGE(C40:N40) -> 4.5
B41: Total 2026 | C41: =SUM(C31:C40) -> 46.94 | D41: =SUM(D31:D40) -> 50.88 | E41: =SUM(E31:E40) -> 0 | F41: =SUM(F31:F40) -> 0 | G41: =SUM(G31:G40) -> 0 | H41: =SUM(H31:H40) -> 0 | I41: =SUM(I31:I40) -> 0 | J41: =SUM(J31:J40) -> 0 | ... O41: =SUM(O31:O40) -> 97.82

Sheet Projeções
A1: Linha do Tempo | B1: Valores | C1: Previsão | D1: Limite de Confiança Inferior | E1: Limite de Confiança Superior
A2: 45658 | B2: 1.79
A3: 45689 | B3: 4.33
A4: 45717 | B4: 6.96
A5: 45748 | B5: 9.59
A6: 45778 | B6: 12.44
A7: 45809 | B7: 15.05
A8: 45839 | B8: 21.77
A9: 45870 | B9: 23.89
A10: 45901 | B10: 28.63
A11: 45931 | B11: 32.69
A12: 45962 | B12: 36.18
A13: 45992 | B13: 41.94 | C13: 41.94 | D13: 41.94 | E13: 41.94
A14: 46023 | C14: =_xlfn.FORECAST.ETS(A14,$B$2:$B$13,$A$2:$A$13,1,1) -> 46.04527 | D14: =C14-_xlfn.FORECAST.ETS.CONFINT(A14,$B$2:$B$13,$A$2:$A$13,0.85,1,1) -> 44.021593 | E14: =C14+_xlfn.FORECAST.ETS.CONFINT(A14,$B$2:$B$13,$A$2:$A$13,0.85,1,1) -> 48.068946
A15: 46054 | C15: =_xlfn.FORECAST.ETS(A15,$B$2:$B$13,$A$2:$A$13,1,1) -> 50.717743 | D15: =C15-_xlfn.FORECAST.ETS.CONFINT(A15,$B$2:$B$13,$A$2:$A$13,0.85,1,1) -> 47.60818 | E15: =C15+_xlfn.FORECAST.ETS.CONFINT(A15,$B$2:$B$13,$A$2:$A$13,0.85,1,1) -> 53.827306
A16: 46082 | C16: =_xlfn.FORECAST.ETS(A16,$B$2:$B$13,$A$2:$A$13,1,1) -> 55.390217 | D16: =C16-_xlfn.FORECAST.ETS.CONFINT(A16,$B$2:$B$13,$A$2:$A$13,0.85,1,1) -> 50.80272 | E16: =C16+_xlfn.FORECAST.ETS.CONFINT(A16,$B$2:$B$13,$A$2:$A$13,0.85,1,1) -> 59.977713
A17: 46113 | C17: =_xlfn.FORECAST.ETS(A17,$B$2:$B$13,$A$2:$A$13,1,1) -> 60.06269 | D17: =C17-_xlfn.FORECAST.ETS.CONFINT(A17,$B$2:$B$13,$A$2:$A$13,0.85,1,1) -> 53.716815 | E17: =C17+_xlfn.FORECAST.ETS.CONFINT(A17,$B$2:$B$13,$A$2:$A$13,0.85,1,1) -> 66.408565
A18: 46143 | C18: =_xlfn.FORECAST.ETS(A18,$B$2:$B$13,$A$2:$A$13,1,1) -> 64.735164 | D18: =C18-_xlfn.FORECAST.ETS.CONFINT(A18,$B$2:$B$13,$A$2:$A$13,0.85,1,1) -> 56.404975 | E18: =C18+_xlfn.FORECAST.ETS.CONFINT(A18,$B$2:$B$13,$A$2:$A$13,0.85,1,1) -> 73.065352
A19: 46174 | C19: =_xlfn.FORECAST.ETS(A19,$B$2:$B$13,$A$2:$A$13,1,1) -> 69.407637 | D19: =C19-_xlfn.FORECAST.ETS.CONFINT(A19,$B$2:$B$13,$A$2:$A$13,0.85,1,1) -> 58.897715 | E19: =C19+_xlfn.FORECAST.ETS.CONFINT(A19,$B$2:$B$13,$A$2:$A$13,0.85,1,1) -> 79.917559
A20: 46204 | C20: =_xlfn.FORECAST.ETS(A20,$B$2:$B$13,$A$2:$A$13,1,1) -> 74.080111 | D20: =C20-_xlfn.FORECAST.ETS.CONFINT(A20,$B$2:$B$13,$A$2:$A$13,0.85,1,1) -> 61.214767 | E20: =C20+_xlfn.FORECAST.ETS.CONFINT(A20,$B$2:$B$13,$A$2:$A$13,0.85,1,1) -> 86.945454
A21: 46235 | C21: =_xlfn.FORECAST.ETS(A21,$B$2:$B$13,$A$2:$A$13,1,1) -> 78.752584 | D21: =C21-_xlfn.FORECAST.ETS.CONFINT(A21,$B$2:$B$13,$A$2:$A$13,0.85,1,1) -> 63.370275 | E21: =C21+_xlfn.FORECAST.ETS.CONFINT(A21,$B$2:$B$13,$A$2:$A$13,0.85,1,1) -> 94.134894
A22: 46266 | C22: =_xlfn.FORECAST.ETS(A22,$B$2:$B$13,$A$2:$A$13,1,1) -> 83.425058 | D22: =C22-_xlfn.FORECAST.ETS.CONFINT(A22,$B$2:$B$13,$A$2:$A$13,0.85,1,1) -> 65.375092 | E22: =C22+_xlfn.FORECAST.ETS.CONFINT(A22,$B$2:$B$13,$A$2:$A$13,0.85,1,1) -> 101.47502
A23: 46296 | C23: =_xlfn.FORECAST.ETS(A23,$B$2:$B$13,$A$2:$A$13,1,1) -> 88.097531 | D23: =C23-_xlfn.FORECAST.ETS.CONFINT(A23,$B$2:$B$13,$A$2:$A$13,0.85,1,1) -> 67.23795 | E23: =C23+_xlfn.FORECAST.ETS.CONFINT(A23,$B$2:$B$13,$A$2:$A$13,0.85,1,1) -> 108.95711
A24: 46327 | C24: =_xlfn.FORECAST.ETS(A24,$B$2:$B$13,$A$2:$A$13,1,1) -> 92.770005 | D24: =C24-_xlfn.FORECAST.ETS.CONFINT(A24,$B$2:$B$13,$A$2:$A$13,0.85,1,1) -> 68.966104 | E24: =C24+_xlfn.FORECAST.ETS.CONFINT(A24,$B$2:$B$13,$A$2:$A$13,0.85,1,1) -> 116.57391
A25: 46357 | C25: =_xlfn.FORECAST.ETS(A25,$B$2:$B$13,$A$2:$A$13,1,1) -> 97.442478 | D25: =C25-_xlfn.FORECAST.ETS.CONFINT(A25,$B$2:$B$13,$A$2:$A$13,0.85,1,1) -> 70.56573 | E25: =C25+_xlfn.FORECAST.ETS.CONFINT(A25,$B$2:$B$13,$A$2:$A$13,0.85,1,1) -> 124.31923
A26: 46388 | C26: =_xlfn.FORECAST.ETS(A26,$B$2:$B$13,$A$2:$A$13,1,1) -> 102.11495 | D26: =C26-_xlfn.FORECAST.ETS.CONFINT(A26,$B$2:$B$13,$A$2:$A$13,0.85,1,1) -> 72.042182 | E26: =C26+_xlfn.FORECAST.ETS.CONFINT(A26,$B$2:$B$13,$A$2:$A$13,0.85,1,1) -> 132.18772

Sheet Fluxo_TIR
B2: Data | C2: Fluxo
B3: 45665 | C3: -99.61 | D3: 99.61 | E3: -1 | G3: =XIRR(C3:C134,B3:B134) -> 0.053700444
B4: 45665 | C4: -95.83 | D4: 95.83
B5: 45665 | C5: -97.91 | D5: 97.91
B6: 45694 | C6: -98.96 | D6: 98.96
B7: 45694 | C7: -93.74 | D7: 93.74
B8: 45694 | C8: -97.99 | D8: 97.99
B9: 45726 | C9: -101.88 | D9: 101.88
B10: 45726 | C10: -96.31 | D10: 96.31
B11: 45726 | C11: -97.34 | D11: 97.34
B12: 45751 | C12: -100.82 | D12: 100.82
B13: 45751 | C13: -97.65 | D13: 97.65
B14: 45751 | C14: -103.98 | D14: 103.98
B15: 45772 | C15: -17.36 | D15: 17.36
... B73: 46084 | C73: -158.57 | D73: 158.57
B74: 46084 | C74: -159.35
B75: 45679 | C75: 0.86
B76: 45679 | C76: 0.92
B77: 45702 | C77: 0.93
B78: 45713 | C78: 1.56
B79: 45713 | C79: 1.84
B80: 45734 | C80: 1.86
B81: 45741 | C81: 2.34
B82: 45741 | C82: 2.76
B83: 45761 | C83: 2.79
B84: 45772 | C84: 3.12
B85: 45772 | C85: 3.68
... B133: 46078 | C133: 12.88
B134: 46085 | C134: =SUM(D3:D73) -> 6539.39
